quick_api_tests/__init__.py
quick_api_tests/cli/__init__.py
quick_api_tests/cli/main.py
quick_api_tests/generators/__init__.py
quick_api_tests/generators/base.py
quick_api_tests/generators/grpc/__init__.py
quick_api_tests/generators/grpc/extractor.py
quick_api_tests/generators/grpc/generator.py
quick_api_tests/generators/grpc/proto_recover.py
quick_api_tests/generators/http/__init__.py
quick_api_tests/generators/http/filters.py
quick_api_tests/generators/http/parser.py
quick_api_tests/generators/http/rest_codegen.py
quick_api_tests/generators/logic_generator/__init__.py
quick_api_tests/generators/logic_generator/logic_generator.py
quick_api_tests/generators/templates/api_helper.jinja2
quick_api_tests/generators/templates/base_setup.jinja2
quick_api_tests/generators/templates/grpc_client.jinja2
quick_api_tests/generators/templates/grpc_helper_method.jinja2
quick_api_tests/generators/templates/http_apis_init.jinja2
quick_api_tests/generators/templates/http_client.jinja2
quick_api_tests/generators/templates/http_helper_method.jinja2
quick_api_tests/generators/templates/service_facade.jinja2
quick_api_tests/generators/templates/service_helper.jinja2
quick_api_tests/generators/templates/tests.jinja2
quick_api_tests/generators/test_generator/generator.py
quick_api_tests/generators/utils.py
quick_api_tests/grpc_client/__init__.py
quick_api_tests/grpc_client/client.py
quick_api_tests/grpc_client/interceptors/__init__.py
quick_api_tests/grpc_client/interceptors/default_headers.py
quick_api_tests/grpc_client/interceptors/log_utils.py
quick_api_tests/grpc_client/interceptors/logging.py
quick_api_tests/http_client/__init__.py
quick_api_tests/http_client/client_async.py
quick_api_tests/http_client/client_sync.py
quick_api_tests/http_client/configuration.py
quick_api_tests/logger/__init__.py
quick_api_tests/logger/log.py
quick_api_tests-0.3.2.dist-info/LICENSE
quick_api_tests-0.3.2.dist-info/METADATA
quick_api_tests-0.3.2.dist-info/WHEEL
quick_api_tests-0.3.2.dist-info/entry_points.txt
quick_api_tests-0.3.2.dist-info/RECORD
